odoo/addons/connector_routific/README.rst
odoo/addons/connector_routific/__init__.py
odoo/addons/connector_routific/__manifest__.py
odoo/addons/connector_routific/data/sequence.xml
odoo/addons/connector_routific/i18n/connector_routific.pot
odoo/addons/connector_routific/i18n/es.po
odoo/addons/connector_routific/models/__init__.py
odoo/addons/connector_routific/models/product_attribute.py
odoo/addons/connector_routific/models/res_partner.py
odoo/addons/connector_routific/models/routific_config.py
odoo/addons/connector_routific/models/routific_project.py
odoo/addons/connector_routific/models/routific_project_driver.py
odoo/addons/connector_routific/models/stock_picking.py
odoo/addons/connector_routific/readme/CONFIGURE.rst
odoo/addons/connector_routific/readme/CONTRIBUTORS.rst
odoo/addons/connector_routific/readme/DESCRIPTION.rst
odoo/addons/connector_routific/readme/USAGE.rst
odoo/addons/connector_routific/security/ir.model.access.csv
odoo/addons/connector_routific/static/description/icon.png
odoo/addons/connector_routific/static/description/index.html
odoo/addons/connector_routific/tests/__init__.py
odoo/addons/connector_routific/tests/test_connector_routific.py
odoo/addons/connector_routific/views/product_attribute_views.xml
odoo/addons/connector_routific/views/res_partner_view.xml
odoo/addons/connector_routific/views/routific_config_views.xml
odoo/addons/connector_routific/views/routific_driver_views.xml
odoo/addons/connector_routific/views/routific_project_driver_view.xml
odoo/addons/connector_routific/views/routific_project_views.xml
odoo/addons/connector_routific/views/stock_picking_views.xml
odoo/addons/connector_routific/wizards/__init__.py
odoo/addons/connector_routific/wizards/routific_project_creator.py
odoo/addons/connector_routific/wizards/routific_project_creator_view.xml
odoo13_addon_connector_routific-13.0.1.0.1.dev4.dist-info/METADATA
odoo13_addon_connector_routific-13.0.1.0.1.dev4.dist-info/WHEEL
odoo13_addon_connector_routific-13.0.1.0.1.dev4.dist-info/top_level.txt
odoo13_addon_connector_routific-13.0.1.0.1.dev4.dist-info/RECORD
